betterset/__init__.py
betterset-0.1.0.dist-info/METADATA
betterset-0.1.0.dist-info/WHEEL
betterset-0.1.0.dist-info/licenses/LICENSE
betterset-0.1.0.dist-info/RECORD
