Metadata-Version: 2.4
Name: betterset
Version: 0.1.0
Summary: Extended set operations: algebraic, functional, and utilities on top of Python set
Project-URL: Homepage, https://github.com/izzet/betterset
Project-URL: Repository, https://github.com/izzet/betterset
Project-URL: Documentation, https://github.com/izzet/betterset#readme
Project-URL: Bug Tracker, https://github.com/izzet/betterset/issues
Author-email: Izzet Yildirim <izzetcyildirim@gmail.com>
Maintainer-email: Izzet Yildirim <izzetcyildirim@gmail.com>
License: MIT
License-File: LICENSE
Keywords: algebra,cartesian,functional,powerset,python,set
Classifier: Development Status :: 3 - Alpha
Classifier: Intended Audience :: Developers
Classifier: License :: OSI Approved :: MIT License
Classifier: Programming Language :: Python :: 3
Classifier: Programming Language :: Python :: 3.8
Classifier: Programming Language :: Python :: 3.9
Classifier: Programming Language :: Python :: 3.10
Classifier: Programming Language :: Python :: 3.11
Classifier: Programming Language :: Python :: 3.12
Classifier: Topic :: Software Development :: Libraries :: Python Modules
Requires-Python: >=3.8
